{"config":{"output_file":null,"full_docs":false,"pub_only":true,"reachable_only":true,"distro_crate":false,"signatures":false,"borrow_data":false},"version":"0.19.0","compilation":{"directory":"/Users/watanabeshunsuke/.cargo/registry/src/github.com-1ecc6299db9ec823/proc-macro2-1.0.10","program":"/Users/watanabeshunsuke/.rustup/toolchains/nightly-x86_64-apple-darwin/bin/rls","arguments":["--crate-name","build_script_build","--edition=2018","/Users/watanabeshunsuke/.cargo/registry/src/github.com-1ecc6299db9ec823/proc-macro2-1.0.10/build.rs","--json=diagnostic-rendered-ansi","--crate-type","bin","--emit=dep-info,link","-C","debuginfo=2","--cfg","feature=\"default\"","--cfg","feature=\"proc-macro\"","-C","metadata=819b7acbdb95f352","-C","extra-filename=-819b7acbdb95f352","--out-dir","/Users/watanabeshunsuke/rust/training/database/postgres/target/rls/debug/build/proc-macro2-819b7acbdb95f352","-L","dependency=/Users/watanabeshunsuke/rust/training/database/postgres/target/rls/debug/deps","--cap-lints","allow","--error-format=json","--sysroot","/Users/watanabeshunsuke/.rustup/toolchains/nightly-x86_64-apple-darwin"],"output":"/Users/watanabeshunsuke/rust/training/database/postgres/target/rls/debug/build/proc-macro2-819b7acbdb95f352/build_script_build-819b7acbdb95f352"},"prelude":{"crate_id":{"name":"build_script_build","disambiguator":[16342007447715825308,18153813068023142809]},"crate_root":"/Users/watanabeshunsuke/.cargo/registry/src/github.com-1ecc6299db9ec823/proc-macro2-1.0.10","external_crates":[{"file_name":"/Users/watanabeshunsuke/.cargo/registry/src/github.com-1ecc6299db9ec823/proc-macro2-1.0.10/build.rs","num":1,"id":{"name":"std","disambiguator":[4764348733193513031,634526535461708798]}},{"file_name":"/Users/watanabeshunsuke/.cargo/registry/src/github.com-1ecc6299db9ec823/proc-macro2-1.0.10/build.rs","num":2,"id":{"name":"core","disambiguator":[1442326455198172401,16827337489037353969]}},{"file_name":"/Users/watanabeshunsuke/.cargo/registry/src/github.com-1ecc6299db9ec823/proc-macro2-1.0.10/build.rs","num":3,"id":{"name":"compiler_builtins","disambiguator":[12054269309559547164,403528097874103758]}},{"file_name":"/Users/watanabeshunsuke/.cargo/registry/src/github.com-1ecc6299db9ec823/proc-macro2-1.0.10/build.rs","num":4,"id":{"name":"rustc_std_workspace_core","disambiguator":[18119295300660958056,15936712641001091472]}},{"file_name":"/Users/watanabeshunsuke/.cargo/registry/src/github.com-1ecc6299db9ec823/proc-macro2-1.0.10/build.rs","num":5,"id":{"name":"alloc","disambiguator":[8467185899157176901,5449114614531918343]}},{"file_name":"/Users/watanabeshunsuke/.cargo/registry/src/github.com-1ecc6299db9ec823/proc-macro2-1.0.10/build.rs","num":6,"id":{"name":"libc","disambiguator":[6399579860591818883,1861182124498570286]}},{"file_name":"/Users/watanabeshunsuke/.cargo/registry/src/github.com-1ecc6299db9ec823/proc-macro2-1.0.10/build.rs","num":7,"id":{"name":"unwind","disambiguator":[5934281359445186259,17569308659596391902]}},{"file_name":"/Users/watanabeshunsuke/.cargo/registry/src/github.com-1ecc6299db9ec823/proc-macro2-1.0.10/build.rs","num":8,"id":{"name":"cfg_if","disambiguator":[13411228280306895108,18307809851336013232]}},{"file_name":"/Users/watanabeshunsuke/.cargo/registry/src/github.com-1ecc6299db9ec823/proc-macro2-1.0.10/build.rs","num":9,"id":{"name":"backtrace","disambiguator":[6991553045555133022,10391329883647596551]}},{"file_name":"/Users/watanabeshunsuke/.cargo/registry/src/github.com-1ecc6299db9ec823/proc-macro2-1.0.10/build.rs","num":10,"id":{"name":"rustc_demangle","disambiguator":[12965431198908124934,18004796543845665014]}},{"file_name":"/Users/watanabeshunsuke/.cargo/registry/src/github.com-1ecc6299db9ec823/proc-macro2-1.0.10/build.rs","num":11,"id":{"name":"backtrace_sys","disambiguator":[17525835346239097561,8778688016660685031]}},{"file_name":"/Users/watanabeshunsuke/.cargo/registry/src/github.com-1ecc6299db9ec823/proc-macro2-1.0.10/build.rs","num":12,"id":{"name":"hashbrown","disambiguator":[16866301928884371641,12906074390672532027]}},{"file_name":"/Users/watanabeshunsuke/.cargo/registry/src/github.com-1ecc6299db9ec823/proc-macro2-1.0.10/build.rs","num":13,"id":{"name":"rustc_std_workspace_alloc","disambiguator":[14707452596726515572,12648684369639413126]}},{"file_name":"/Users/watanabeshunsuke/.cargo/registry/src/github.com-1ecc6299db9ec823/proc-macro2-1.0.10/build.rs","num":14,"id":{"name":"panic_unwind","disambiguator":[6619135282819627752,14012907817905728436]}}],"span":{"file_name":"/Users/watanabeshunsuke/.cargo/registry/src/github.com-1ecc6299db9ec823/proc-macro2-1.0.10/build.rs","byte_start":1502,"byte_end":4194,"line_start":33,"line_end":129,"column_start":1,"column_end":2}},"imports":[],"defs":[{"kind":"Mod","id":{"krate":0,"index":0},"span":{"file_name":"/Users/watanabeshunsuke/.cargo/registry/src/github.com-1ecc6299db9ec823/proc-macro2-1.0.10/build.rs","byte_start":1502,"byte_end":4194,"line_start":33,"line_end":129,"column_start":1,"column_end":2},"name":"","qualname":"::","value":"/Users/watanabeshunsuke/.cargo/registry/src/github.com-1ecc6299db9ec823/proc-macro2-1.0.10/build.rs","parent":null,"children":[{"krate":0,"index":1},{"krate":0,"index":2},{"krate":0,"index":3},{"krate":0,"index":4},{"krate":0,"index":7},{"krate":0,"index":8},{"krate":0,"index":9},{"krate":0,"index":10},{"krate":0,"index":13},{"krate":0,"index":14}],"decl_id":null,"docs":"","sig":null,"attributes":[]}],"impls":[],"refs":[],"macro_refs":[],"relations":[]}